{
  "project_info": {
    "project_number": "974076482456",
    "firebase_url": "https://anoroctestnotifcation.firebaseio.com",
    "project_id": "anoroctestnotifcation",
    "storage_bucket": "anoroctestnotifcation.appspot.com"
  },
  "client": [
    {
      "client_info": {
        "mobilesdk_app_id": "1:974076482456:android:2a379bf534ef77ae9411ed",
        "android_client_info": {
          "package_name": "com.anorocmobileapp"
        }
      },
      "oauth_client": [
        {
          "client_id": "974076482456-q3j3n0rv9qc1rbc8d8a5p03ksc9dduel.apps.googleusercontent.com",
          "client_type": 3
        }
      ],
      "api_key": [
        {
          "current_key": "AIzaSyAdXkzcZ1hFpxjqd3JO8YNLf3CmjBYzFHA"
        }
      ],
      "services": {
        "appinvite_service": {
          "other_platform_oauth_client": [
            {
              "client_id": "974076482456-q3j3n0rv9qc1rbc8d8a5p03ksc9dduel.apps.googleusercontent.com",
              "client_type": 3
            }
          ]
        }
      }
    }
  ],
  "configuration_version": "1"
}